README
setup.py
models/__init__.py
models/base.py
models/exceptions.py
models/props.py
models/references.py
models.egg-info/PKG-INFO
models.egg-info/SOURCES.txt
models.egg-info/dependency_links.txt
models.egg-info/top_level.txt
models/backends/__init__.py
models/backends/base.py
models/backends/tokyo_cabinet.py
models/backends/tokyo_tyrant.py
models/utils/__init__.py
models/utils/iterators.py